edgar_client/__init__.py
edgar_client/client.py
edgar_client/py.typed
edgar_client-0.0.5.dist-info/METADATA
edgar_client-0.0.5.dist-info/WHEEL
edgar_client-0.0.5.dist-info/licenses/LICENSE
edgar_client-0.0.5.dist-info/RECORD
