Metadata-Version: 2.4
Name: edgar-client
Version: 0.0.5
Summary: A Python client for retrieving filings from the SEC Edgar.
Project-URL: Homepage, https://github.com/joeychilson/edgar-client
Project-URL: Documentation, https://github.com/joeychilson/edgar-client/blob/main/README.md
Project-URL: Repository, https://github.com/joeychilson/edgar-client.git
Project-URL: Issues, https://github.com/joeychilson/edgar-client/issues
Author-email: Joey Chilson <joeychilson@outlook.com>
License: MIT License
License-File: LICENSE
Classifier: Development Status :: 3 - Alpha
Classifier: License :: OSI Approved :: MIT License
Classifier: Programming Language :: Python
Classifier: Programming Language :: Python :: 3
Classifier: Programming Language :: Python :: 3 :: Only
Classifier: Programming Language :: Python :: 3.9
Classifier: Programming Language :: Python :: 3.10
Classifier: Programming Language :: Python :: 3.11
Classifier: Programming Language :: Python :: 3.12
Classifier: Programming Language :: Python :: 3.13
Requires-Python: >=3.9
Requires-Dist: httpx>=0.28.1
Requires-Dist: pydantic>=2.10.4
Requires-Dist: ratelimit>=2.2.1
